setup.py
distributions_perl/Binomialdistribution.py
distributions_perl/Gaussiandistribution.py
distributions_perl/Generaldistribution.py
distributions_perl/__init__.py
distributions_perl.egg-info/PKG-INFO
distributions_perl.egg-info/SOURCES.txt
distributions_perl.egg-info/dependency_links.txt
distributions_perl.egg-info/not-zip-safe
distributions_perl.egg-info/top_level.txt