Metadata-Version: 1.0
Name: distributions-perl
Version: 0.1
Summary: Gaussian distributions
Home-page: UNKNOWN
Author: Gustavo Perl
Author-email: gustavopperl@gmail.com
License: UNKNOWN
Platform: UNKNOWN
